nn_parts/__init__.py
nn_parts/activation_relu.py
nn_parts/activation_sigmoid.py
nn_parts/activation_softmax.py
nn_parts/cost_cross_entropy.py
nn_parts/cost_quadratic.py
nn_parts/denselayer.py
nn_parts/metric_accuracy.py
nn_parts-2024.0.3.dist-info/METADATA
nn_parts-2024.0.3.dist-info/WHEEL
nn_parts-2024.0.3.dist-info/licenses/LICENSE.txt
nn_parts-2024.0.3.dist-info/RECORD
