Metadata-Version: 2.3
Name: nn_parts
Version: 2024.0.3
Summary: Diagnois and Triage Neural Network
Project-URL: Homepage, https://example.com
Project-URL: Documentation, https://readthedocs.org
Project-URL: Repository, https://github.com/me/spam.git
Project-URL: Changelog, https://github.com/me/spam/blob/master/CHANGELOG.md
Author-email: Pankaj Singh <pankajpriscilla@gmail.com>
Maintainer-email: Pankaj Singh <pankajpriscilla@gmail.com>
License-File: LICENSE.txt
Keywords: Neural Network
Classifier: Development Status :: 3 - Alpha
Classifier: Intended Audience :: Developers
Classifier: Programming Language :: Python
Requires-Python: >=3.8
Requires-Dist: numpy
